{
    "prepare_queue": {
        "installed": [],
        "uninstalled": []
    },
    "config_munge": {
        "files": {}
    },
    "installed_plugins": {
        "cordova-plugin-console": {
            "PACKAGE_NAME": "io.ionic.starter"
        },
        "cordova-plugin-device": {
            "PACKAGE_NAME": "io.ionic.starter"
        },
        "cordova-plugin-splashscreen": {
            "PACKAGE_NAME": "io.ionic.starter"
        },
        "cordova-plugin-statusbar": {
            "PACKAGE_NAME": "io.ionic.starter"
        },
        "cordova-plugin-whitelist": {
            "PACKAGE_NAME": "io.ionic.starter"
        },
        "ionic-plugin-keyboard": {
            "PACKAGE_NAME": "io.ionic.starter"
        },
        "cordova-plugin-facebook4": {
            "APP_ID": "194426564367310",
            "APP_NAME": "eventHub",
            "PACKAGE_NAME": "io.ionic.starter"
        },
        "cordova-plugin-nativestorage": {
            "PACKAGE_NAME": "com.ionicframework.newproject531488"
        },
        "cordova-plugin-network-information": {
            "PACKAGE_NAME": "com.ionicframework.newproject531488"
        },
        "phonegap-plugin-push": {
            "SENDER_ID": "972428714274",
            "PACKAGE_NAME": "com.ionicframework.newproject531488"
        }
    },
    "dependent_plugins": {}
}